django_googlecloud_storage-0.0.1-py3.5-nspkg.pth
django/googlecloud/__init__.py
django/googlecloud/storage.py
django_googlecloud_storage-0.0.1.dist-info/DESCRIPTION.rst
django_googlecloud_storage-0.0.1.dist-info/METADATA
django_googlecloud_storage-0.0.1.dist-info/RECORD
django_googlecloud_storage-0.0.1.dist-info/WHEEL
django_googlecloud_storage-0.0.1.dist-info/metadata.json
django_googlecloud_storage-0.0.1.dist-info/namespace_packages.txt
django_googlecloud_storage-0.0.1.dist-info/top_level.txt
