Metadata-Version: 2.0
Name: django-googlecloud-storage
Version: 0.0.1
Summary: Google Cloud Storage file backend for Django based on google-cloud
Home-page: https://github.com/sureshvv/django-google-cloud-storage/
Author: Suresh V
Author-email: suresh@grafware.com
License: GPL
Keywords: django,appengine,google,cloud storage
Platform: UNKNOWN
Requires-Dist: google-cloud-storage (>=0.20.0)
